{
  "pexels-andrea-piacquadio-774909.jpg": {
    "mime": "image/jpeg"
  },
  "logoipsum-213.svg": {
    "mime": "image/svg+xml"
  },
  "logoipsum-219.svg": {
    "mime": "image/svg+xml"
  },
  "logoipsum-218.svg": {
    "mime": "image/svg+xml"
  },
  "logoipsum-239.svg": {
    "mime": "image/svg+xml"
  },
  "icons8-filled-circle-30.png": {
    "mime": "image/png"
  },
  "icons8-filled-circle-16.png": {
    "mime": "image/png"
  },
  "new.png": {
    "mime": "image/png"
  },
  "new1.png": {
    "mime": "image/png"
  },
  "new2.png": {
    "mime": "image/png"
  },
  "l1.svg": {
    "mime": "image/svg+xml"
  },
  "l2.svg": {
    "mime": "image/svg+xml"
  },
  "l3.svg": {
    "mime": "image/svg+xml"
  },
  "pexels-tom-swinnen-2249961.jpg": {
    "mime": "image/jpeg"
  },
  "pexels-bruno-thethe-1910225.jpg": {
    "mime": "image/jpeg"
  },
  "pexels-wendy-wei-2974618.jpg": {
    "mime": "image/jpeg"
  },
  "chevron-left.svg": {
    "mime": "image/svg+xml"
  },
  "chevron-right.svg": {
    "mime": "image/svg+xml"
  },
  "p1.png": {
    "mime": "image/png"
  },
  "p2.png": {
    "mime": "image/png"
  },
  "p3.png": {
    "mime": "image/png"
  },
  "p4.png": {
    "mime": "image/png"
  },
  "book.png": {
    "mime": "image/png"
  },
  "briefcase.png": {
    "mime": "image/png"
  },
  "w1.svg": {
    "mime": "image/svg+xml"
  },
  "w2.svg": {
    "mime": "image/svg+xml"
  },
  "w3.svg": {
    "mime": "image/svg+xml"
  },
  "t2.png": {
    "mime": "image/png"
  },
  "t1.jpeg": {
    "mime": "image/jpeg"
  },
  "60ad1c2b0e1d633fc7ef2e69_Group 160-min-p-500.jpeg": {
    "mime": "image/jpeg"
  }
}